Metadata-Version: 2.1
Name: zxinglight
Version: 1.1.0
Summary: A simple ZXing C++ wrapper
Home-page: https://github.com/lubo/zxinglight
Author: Ľubomír Kučera
Author-email: lubomir.kucera.jr@gmail.com
License: MIT
Keywords: zxing,barcode,QR code
Platform: UNKNOWN
Classifier: Development Status :: 5 - Production/Stable
Classifier: Intended Audience :: Developers
Classifier: License :: OSI Approved :: MIT License
Classifier: Natural Language :: English
Classifier: Operating System :: OS Independent
Classifier: Programming Language :: C++
Classifier: Programming Language :: Python :: 3.5
Classifier: Programming Language :: Python :: 3.6
Classifier: Programming Language :: Python :: 3.7
Classifier: Topic :: Scientific/Engineering :: Image Recognition
Provides-Extra: test
Provides-Extra: docs
